pyrosexmod/__init__.py
pyrosexmod/teledl.py
pyrosexmod/filters/__init__.py
pyrosexmod/filters/filters.py
pyrosexmod/helpers/__init__.py
pyrosexmod/helpers/helpers.py
pyrosexmod/listen/__init__.py
pyrosexmod/listen/listen.py
pyrosexmod/utils/__init__.py
pyrosexmod/utils/utils.py
pyrosexmod-0.2.1.dist-info/COPYING
pyrosexmod-0.2.1.dist-info/COPYING.lesser
pyrosexmod-0.2.1.dist-info/METADATA
pyrosexmod-0.2.1.dist-info/NOTICE
pyrosexmod-0.2.1.dist-info/WHEEL
pyrosexmod-0.2.1.dist-info/top_level.txt
pyrosexmod-0.2.1.dist-info/RECORD
