Metadata-Version: 2.1
Name: pyrosexmod
Version: 0.2.1
Summary: A monkeypatcher add-on for Pyrosex
Home-page: https://github.com/OnTheHerd/pyrosexmod
Author: OTH
Author-email: oth@pyrosex.org
License: LGPLv3+
Classifier: Programming Language :: Python :: 3
Classifier: License :: OSI Approved :: GNU Lesser General Public License v3 or later (LGPLv3+)
Classifier: Operating System :: OS Independent
Requires-Python: >=3.6
License-File: COPYING
License-File: COPYING.lesser
License-File: NOTICE
Requires-Dist: pyrosex (>=0.0.3)
Requires-Dist: youtube-dlc
